patched_yolo_infer/__init__.py
patched_yolo_infer/functions_extra.py
patched_yolo_infer/elements/CropElement.py
patched_yolo_infer/elements/__init__.py
patched_yolo_infer/nodes/CombineDetections.py
patched_yolo_infer/nodes/MakeCropsDetectThem.py
patched_yolo_infer/nodes/__init__.py
patched_yolo_infer-1.3.8.dist-info/LICENSE.txt
patched_yolo_infer-1.3.8.dist-info/METADATA
patched_yolo_infer-1.3.8.dist-info/WHEEL
patched_yolo_infer-1.3.8.dist-info/top_level.txt
patched_yolo_infer-1.3.8.dist-info/RECORD
