Metadata-Version: 2.1
Name: patched-yolo-infer
Version: 1.3.8
Summary: Patch-Based-Inference for detection/segmentation of small objects in images.
Home-page: https://github.com/Koldim2001/YOLO-Patch-Based-Inference
Author: Koldim2001
License: AGPL-3.0 license
Keywords: python,YOLOv8,YOLOv9,YOLOv10,YOLO11,YOLO-seg,YOLO-pose,rtdetr,fastsam,sahi,object detection,instance segmentation,patch-based inference,patch-based,small object detection,image patching,YOLO visualization,YOLO-seg visualization,YOLO-pose visualization,slice-based inference,slicing inference,inference visualization,patchify,ultralytics,computer-vision
Classifier: Development Status :: 5 - Production/Stable
Classifier: Intended Audience :: Developers
Classifier: Programming Language :: Python :: 3
Classifier: License :: OSI Approved :: GNU Affero General Public License v3 or later (AGPLv3+)
Classifier: Operating System :: OS Independent
Requires-Python: >=3.8
License-File: LICENSE.txt
Requires-Dist: numpy <2.0
Requires-Dist: tqdm
Requires-Dist: opencv-python
Requires-Dist: matplotlib
Requires-Dist: ultralytics
